Workbook

Sheet Summary
B2: IONIC WEALTH
B3: Portfolio Snapshot — NDPMS Review
B5: Client | C5: Shreyas Gupta
B6: As of | C6: 30 July 2026
B7: Account type | C7: NDPMS (Non-Discretionary PMS)
B9: PORTFOLIO STRUCTURE
B10: Total holdings | C10: =COUNTA('Equity Holdings'!B7:B16)+COUNTA('Mutual Funds'!B7:B10)
B11: Stocks | C11: =COUNTA('Equity Holdings'!B7:B16)
B12: Mutual funds | C12: =COUNTA('Mutual Funds'!B7:B10)
B13: Weighting | C13: Equal weight (all holdings)
B15: SLEEVE SPLIT
B16: Sleeve | C16: Weight | D16: Holdings
B17: Equity (direct stocks) | C17: =SUM('Equity Holdings'!D7:D16) | D17: =COUNTA('Equity Holdings'!B7:B16)
B18: Mutual funds | C18: =SUM('Mutual Funds'!E7:E10) | D18: =COUNTA('Mutual Funds'!B7:B10)
B19: Total | C19: =C17+C18 | D19: =D17+D18
B21: WATCH-OUTS (structure only)
B22: • | C22: Two Small Cap funds held (LIC + Nippon) — category concentration in small-cap.
B23: • | C23: IT sector doubled up (Infosys + KPIT Technologies) — see Sector Exposure sheet.
B24: • | C24: LIC Small Cap is a Regular plan — cost-drag / switch-to-Direct candidate (confirm via fund framework).
B25: • | C25: Scores & recommendations NOT filled — require Scorecard-750 + QFRA run (see Assumptions).

Sheet Equity Holdings
B2: EQUITY BOOK — Direct Stocks
B3: Shreyas Gupta · Equal weight · as of 30 July 2026
B6: Ticker | C6: Company | D6: Weight | E6: Sector | F6: Ionic Score | G6: Recommendation | H6: Trim-to / Notes
B7: KPI GREEN | C7: KPI Green Energy Ltd | D7: =1/Summary!$C$10 | E7: Power / Renewable Energy
B8: INFOSYS | C8: Infosys Ltd | D8: =1/Summary!$C$10 | E8: Information Technology
B9: RELIANCE | C9: Reliance Industries Ltd | D9: =1/Summary!$C$10 | E9: Oil, Gas & Consumable Fuels
B10: KPIT TECH | C10: KPIT Technologies Ltd | D10: =1/Summary!$C$10 | E10: Information Technology
B11: JYOTI RESINS | C11: Jyoti Resins & Adhesives Ltd | D11: =1/Summary!$C$10 | E11: Chemicals
B12: KALYAN JEWEL | C12: Kalyan Jewellers India Ltd | D12: =1/Summary!$C$10 | E12: Consumer Durables
B13: GLENMARK | C13: Glenmark Pharmaceuticals Ltd | D13: =1/Summary!$C$10 | E13: Pharma & Healthcare
B14: VODAFONE IDEA | C14: Vodafone Idea Ltd | D14: =1/Summary!$C$10 | E14: Telecommunication
B15: ANANT RAJ | C15: Anant Raj Ltd | D15: =1/Summary!$C$10 | E15: Realty
B16: GODREJ IND | C16: Godrej Industries Ltd | D16: =1/Summary!$C$10 | E16: Diversified / Chemicals
B17: TOTAL | C17: =COUNTA(B7:B16)&" stocks" | D17: =SUM(D7:D16)
F19: Yellow cells: filled by the Scorecard-750 run.

Sheet Mutual Funds
B2: FUND BOOK — Mutual Funds
B3: Shreyas Gupta · Equal weight · as of 30 July 2026
B6: Scheme | C6: AMC | D6: Category | E6: Weight | F6: Plan | G6: Fund Score /100 | H6: Verdict / Notes
B7: WhiteOak Capital Multi Asset Allocation Fund | C7: WhiteOak Capital | D7: Multi Asset Allocation | E7: =1/Summary!$C$10 | F7: Direct
B8: LIC MF Small Cap Fund | C8: LIC Mutual Fund | D8: Small Cap | E8: =1/Summary!$C$10 | F8: Regular
B9: Nippon India Small Cap Fund | C9: Nippon India | D9: Small Cap | E9: =1/Summary!$C$10 | F9: Not stated
B10: HSBC Large Cap Fund | C10: HSBC Mutual Fund | D10: Large Cap | E10: =1/Summary!$C$10 | F10: Not stated
B11: TOTAL | C11: =COUNTA(B7:B10)&" funds" | E11: =SUM(E7:E10)
B13: Verdict rule: a fund Sell ships only when BOTH fund frameworks agree (else Hold).
B14: Yellow cells: filled by the fund-quality run.

Sheet Sector Exposure
B2: SECTOR EXPOSURE — Equity Sleeve
B3: Direct stocks only, by weight
B6: Sector | C6: Weight | D6: Count
B7: Power / Renewable Energy | C7: =SUMIF('Equity Holdings'!$E$7:$E$16,B7,'Equity Holdings'!$D$7:$D$16) | D7: =COUNTIF('Equity Holdings'!$E$7:$E$16,B7)
B8: Information Technology | C8: =SUMIF('Equity Holdings'!$E$7:$E$16,B8,'Equity Holdings'!$D$7:$D$16) | D8: =COUNTIF('Equity Holdings'!$E$7:$E$16,B8)
B9: Oil, Gas & Consumable Fuels | C9: =SUMIF('Equity Holdings'!$E$7:$E$16,B9,'Equity Holdings'!$D$7:$D$16) | D9: =COUNTIF('Equity Holdings'!$E$7:$E$16,B9)
B10: Chemicals | C10: =SUMIF('Equity Holdings'!$E$7:$E$16,B10,'Equity Holdings'!$D$7:$D$16) | D10: =COUNTIF('Equity Holdings'!$E$7:$E$16,B10)
B11: Consumer Durables | C11: =SUMIF('Equity Holdings'!$E$7:$E$16,B11,'Equity Holdings'!$D$7:$D$16) | D11: =COUNTIF('Equity Holdings'!$E$7:$E$16,B11)
B12: Pharma & Healthcare | C12: =SUMIF('Equity Holdings'!$E$7:$E$16,B12,'Equity Holdings'!$D$7:$D$16) | D12: =COUNTIF('Equity Holdings'!$E$7:$E$16,B12)
B13: Telecommunication | C13: =SUMIF('Equity Holdings'!$E$7:$E$16,B13,'Equity Holdings'!$D$7:$D$16) | D13: =COUNTIF('Equity Holdings'!$E$7:$E$16,B13)
B14: Realty | C14: =SUMIF('Equity Holdings'!$E$7:$E$16,B14,'Equity Holdings'!$D$7:$D$16) | D14: =COUNTIF('Equity Holdings'!$E$7:$E$16,B14)
B15: Diversified / Chemicals | C15: =SUMIF('Equity Holdings'!$E$7:$E$16,B15,'Equity Holdings'!$D$7:$D$16) | D15: =COUNTIF('Equity Holdings'!$E$7:$E$16,B15)
B16: Equity total | C16: =SUM(C7:C15) | D16: =SUM(D7:D15)

Sheet Assumptions
B2: ASSUMPTIONS & DATA STATUS
B4: Portfolio composition
B5: Client: Shreyas Gupta. As-of date: 30 July 2026. Account: NDPMS.
B6: You asked for '15 stocks / 12 stocks' but named 10 distinct companies (after merging
B7: RELIANCE and 'RELIANCE INDUSTRIES' into one holding — they are the same company).
B8: This file is built with those 10 real stocks. To reach 15, add the missing names and
B9: the equal weights will re-balance automatically (weight = 1 / total-holdings count).
B10: 4 mutual funds included exactly as named.
B11: Weighting
B12: 'All equal weight' read as equal weight across ALL holdings: each = 1 / total holdings.
B13: With 10 stocks + 4 funds = 14 holdings, each holding = 7.14%; equity sleeve 71.4%,
B14: fund sleeve 28.6%. Change the split by editing weights or adding/removing rows.
... B29: LIC Small Cap held in Regular plan = higher cost; Direct-plan switch is a common review item.
